acore_server_bootstrap/__init__.py
acore_server_bootstrap/_version.py
acore_server_bootstrap/api.py
acore_server_bootstrap/logger.py
acore_server_bootstrap/logger_root.py
acore_server_bootstrap/logger_ubuntu.py
acore_server_bootstrap/paths.py
acore_server_bootstrap/remoter.py
acore_server_bootstrap/actions/__init__.py
acore_server_bootstrap/actions/s0_configure_ubuntu/__init__.py
acore_server_bootstrap/actions/s0_configure_ubuntu/api.py
acore_server_bootstrap/actions/s0_configure_ubuntu/impl.py
acore_server_bootstrap/actions/s0_configure_ubuntu/paths.py
acore_server_bootstrap/actions/s0_configure_ubuntu/wserver-run-on-restart.sh
acore_server_bootstrap/actions/s0_configure_ubuntu/wserver_run_on_restart.py
acore_server_bootstrap/actions/s0_configure_ubuntu/wserver_run_on_restart_as_sudo.py
acore_server_bootstrap/actions/s1_configure_db/__init__.py
acore_server_bootstrap/actions/s1_configure_db/api.py
acore_server_bootstrap/actions/s1_configure_db/impl.py
acore_server_bootstrap/actions/s1_configure_db/paths.py
acore_server_bootstrap/actions/s2_apply_server_config/__init__.py
acore_server_bootstrap/actions/s2_apply_server_config/api.py
acore_server_bootstrap/actions/s2_apply_server_config/impl.py
acore_server_bootstrap/actions/s3_check_server_status/__init__.py
acore_server_bootstrap/actions/s3_check_server_status/api.py
acore_server_bootstrap/actions/s3_check_server_status/impl.py
acore_server_bootstrap/actions/s3_check_server_status/paths.py
acore_server_bootstrap/actions/s3_check_server_status/server_monitor.sh
acore_server_bootstrap/actions/s4_run_server/__init__.py
acore_server_bootstrap/actions/s4_run_server/api.py
acore_server_bootstrap/actions/s4_run_server/auth.sh
acore_server_bootstrap/actions/s4_run_server/impl.py
acore_server_bootstrap/actions/s4_run_server/paths.py
acore_server_bootstrap/actions/s4_run_server/world.sh
acore_server_bootstrap/cli/__init__.py
acore_server_bootstrap/cli/main.py
acore_server_bootstrap/docs/__init__.py
acore_server_bootstrap-1.2.1.dist-info/AUTHORS.rst
acore_server_bootstrap-1.2.1.dist-info/LICENSE.txt
acore_server_bootstrap-1.2.1.dist-info/METADATA
acore_server_bootstrap-1.2.1.dist-info/WHEEL
acore_server_bootstrap-1.2.1.dist-info/entry_points.txt
acore_server_bootstrap-1.2.1.dist-info/top_level.txt
acore_server_bootstrap-1.2.1.dist-info/RECORD
